evalkit/__init__.py
evalkit/kit.py
evalkit/models.py
evalkit/requirements.txt
evalkit/storage.py
aievalkit-0.1.0.dist-info/METADATA
aievalkit-0.1.0.dist-info/WHEEL
aievalkit-0.1.0.dist-info/RECORD
