Metadata-Version: 2.4
Name: aievalkit
Version: 0.1.0
Summary: Core library for EvalKit AI Evaluation.
Project-URL: Homepage, https://github.com/your-username/evalkit
Project-URL: Bug Tracker, https://github.com/your-username/evalkit/issues
Requires-Python: >=3.9
Requires-Dist: httpx>=0.28.1
Requires-Dist: pandas>=1.5.0
Requires-Dist: pydantic>=2.0.0
Requires-Dist: requests>=2.32.3
